{
  "_class": "bitmap",
  "booleanOperation": -1,
  "clippingMask": "{{0, 0}, {1, 1}}",
  "clippingMaskMode": 0,
  "do_objectID": "4B315CE4-FC34-4072-857D-AC0D20877D9F",
  "exportOptions": {
    "_class": "exportOptions",
    "do_objectID": "C837341B-4BEB-4233-B749-D656E0A0A8D6",
    "exportFormats": [
    ],
    "includedLayerIds": [
    ],
    "layerOptions": 0,
    "shouldTrim": false
  },
  "fillReplacesImage": false,
  "frame": {
    "_class": "rect",
    "constrainProportions": true,
    "do_objectID": "EC4EF34F-345D-47F4-93B4-26D83FE37BE7",
    "height": 211,
    "width": 320,
    "x": 0,
    "y": 222
  },
  "hasClippingMask": false,
  "image": {
    "_class": "MSJSONFileReference",
    "_ref": "images/1a4269cbdbfb78c1181a5632903c2f50632c09de.png",
    "_ref_class": "MSImageData"
  },
  "intendedDPI": 72,
  "isFixedToViewport": false,
  "isFlippedHorizontal": false,
  "isFlippedVertical": false,
  "isLocked": false,
  "isVisible": true,
  "layerListExpandedType": 0,
  "name": "Screen Shot 2018-11-07 at 5.19.08 PM",
  "nameIsFixed": false,
  "resizingConstraint": 63,
  "resizingType": 0,
  "rotation": 0,
  "shouldBreakMaskChain": false,
  "style": {
    "_class": "style",
    "do_objectID": "AB61885F-31BC-45A4-923D-F886755D7370",
    "endMarkerType": 0,
    "miterLimit": 10,
    "shadows": [
      {
        "_class": "shadow",
        "blurRadius": 22,
        "color": {
          "_class": "color",
          "alpha": 0.5,
          "blue": 0,
          "green": 0,
          "red": 0
        },
        "contextSettings": {
          "_class": "graphicsContextSettings",
          "blendMode": 0,
          "opacity": 1
        },
        "isEnabled": false,
        "offsetX": 0,
        "offsetY": 11,
        "spread": 0
      }
    ],
    "startMarkerType": 0,
    "windingRule": 1
  }
}