{
  "_class": "shapeGroup",
  "booleanOperation": -1,
  "clippingMaskMode": 0,
  "do_objectID": "4942C57A-0D89-4E7B-A6F2-8918AE2FA640",
  "exportOptions": {
    "_class": "exportOptions",
    "do_objectID": "1AAFB860-2BD1-46ED-B120-E44AFBB59BDB",
    "exportFormats": [
    ],
    "includedLayerIds": [
    ],
    "layerOptions": 0,
    "shouldTrim": false
  },
  "frame": {
    "_class": "rect",
    "constrainProportions": false,
    "do_objectID": "70B616AF-2A79-421F-A65D-0BFE728FF2B6",
    "height": 8.087389868307175,
    "width": 4.423397898049397,
    "x": 0.3165108471074573,
    "y": 0.3449999999999979
  },
  "hasClickThrough": false,
  "hasClippingMask": false,
  "isFixedToViewport": false,
  "isFlippedHorizontal": false,
  "isFlippedVertical": false,
  "isLocked": false,
  "isVisible": true,
  "layerListExpandedType": 1,
  "layers": [
    {
      "class": "shapePath",
      "id": "1E345F30-C693-425A-94E6-2B958F713DFB"
    },
    {
      "class": "shapePath",
      "id": "7F65CB3D-D703-428D-88CD-D48D9E683378"
    }
  ],
  "name": "B",
  "nameIsFixed": false,
  "resizingConstraint": 63,
  "resizingType": 0,
  "rotation": 0,
  "shouldBreakMaskChain": false,
  "style": {
    "_class": "style",
    "do_objectID": "7BB85FC7-2590-4656-BC59-02BB6388D283",
    "endMarkerType": 0,
    "fills": [
      {
        "_class": "fill",
        "color": {
          "_class": "color",
          "alpha": 1,
          "blue": 0.9333333333333333,
          "green": 0.9333333333333333,
          "red": 0.9333333333333333
        },
        "fillType": 0,
        "isEnabled": true,
        "noiseIndex": 0,
        "noiseIntensity": 0,
        "patternFillType": 1,
        "patternTileScale": 1
      }
    ],
    "miterLimit": 10,
    "startMarkerType": 0,
    "windingRule": 0
  },
  "windingRule": 0
}