{
  "_class": "shapeGroup",
  "booleanOperation": -1,
  "clippingMaskMode": 0,
  "do_objectID": "F27EC47D-39A5-46E4-A0C2-9C92C9945572",
  "exportOptions": {
    "_class": "exportOptions",
    "do_objectID": "6B8FC718-CB61-400D-8EB2-B345916418EF",
    "exportFormats": [
    ],
    "includedLayerIds": [
    ],
    "layerOptions": 0,
    "shouldTrim": false
  },
  "frame": {
    "_class": "rect",
    "constrainProportions": false,
    "do_objectID": "094EBB19-3012-485B-B39A-32C98FE5D2DC",
    "height": 18.28026315789477,
    "width": 17.8798954703833,
    "x": 14.89411149825784,
    "y": 0.03039473684210229
  },
  "hasClickThrough": false,
  "hasClippingMask": false,
  "isFixedToViewport": false,
  "isFlippedHorizontal": false,
  "isFlippedVertical": false,
  "isLocked": false,
  "isVisible": true,
  "layerListExpandedType": 1,
  "layers": [
    {
      "class": "shapePath",
      "id": "D6643909-BF5C-4147-B680-71565468EBEF"
    },
    {
      "class": "shapePath",
      "id": "3FC50104-3E0F-436D-A457-AC1F79BB12A6"
    }
  ],
  "name": "A-3",
  "nameIsFixed": false,
  "resizingConstraint": 63,
  "resizingType": 0,
  "rotation": 0,
  "shouldBreakMaskChain": false,
  "style": {
    "_class": "style",
    "do_objectID": "4C15C0FB-88C4-4687-B541-969CD5409410",
    "endMarkerType": 0,
    "fills": [
      {
        "_class": "fill",
        "color": {
          "_class": "color",
          "alpha": 1,
          "blue": 0.9333333333333333,
          "green": 0.9333333333333333,
          "red": 0.9333333333333333
        },
        "fillType": 0,
        "isEnabled": true,
        "noiseIndex": 0,
        "noiseIntensity": 0,
        "patternFillType": 1,
        "patternTileScale": 1
      }
    ],
    "miterLimit": 10,
    "startMarkerType": 0,
    "windingRule": 0
  },
  "windingRule": 0
}